{
  "canvasWidth": 2050,
  "canvasHeight": 5942,
  "bones": [
    {
      "id": "drawn/back-bone",
      "imageWidth": 1138,
      "imageHeight": 1509,
      "connectors": [
        [ 85, 201 ],
        [ 1066, 266 ],
        [ 576, 64 ],
        [ 570, 1477 ]
      ]
    },
    {
      "id": "head-bone",
      "imageWidth": 570,
      "imageHeight": 754,
      "connectors": [
        [ 360, 560 ]
      ]
    },
    {
      "id": "thigh-bone-left",
      "imageWidth": 555,
      "imageHeight": 1578,
      "connectors": [
        [ 454, 140 ],
        [ 166, 1474 ]
      ]
    },
    {
      "id": "thigh-bone-right",
      "imageWidth": 335,
      "imageHeight": 1568,
      "connectors": [
        [ 258, 85 ],
        [ 138, 1463 ]
      ]
    },
    {
      "id": "drawn/finger-bones-right",
      "imageWidth": 210,
      "imageHeight": 520,
      "connectors": [
        [ 63, 55 ]
      ]
    },
    {
      "id": "drawn/foot-bone-left",
      "imageWidth": 402,
      "imageHeight": 429,
      "connectors": [
        [ 110, 28 ]
      ]
    },
    {
      "id": "drawn/foot-bone-right",
      "imageWidth": 553,
      "imageHeight": 346,
      "connectors": [
        [ 450, 28 ]
      ]
    },
    {
      "id": "drawn/forearm-bone-left",
      "imageWidth": 394,
      "imageHeight": 861,
      "connectors": [
        [ 115, 57 ],
        [ 292, 847 ]
      ]
    },
    {
      "id": "drawn/forearm-bone-right",
      "imageWidth": 226,
      "imageHeight": 813,
      "connectors": [
        [ 104, 27 ],
        [ 124, 783 ]
      ]
    },
    {
      "id": "drawn/hand-bone-right",
      "imageWidth": 220,
      "imageHeight": 170,
      "connectors": [
        [ 74, 31 ],
        [ 123, 150 ]
      ]
    },
    {
      "id": "hip-bone",
      "imageWidth": 908,
      "imageHeight": 696,
      "connectors": [
        [ 448, 189 ],
        [ 246, 424 ],
        [ 756, 452 ]
      ]
    },
    {
      "id": "leg-bone-left",
      "imageWidth": 318,
      "imageHeight": 1300,
      "connectors": [
        [ 175, 55 ],
        [ 125, 1243 ]
      ]
    },
    {
      "id": "leg-bone-right",
      "imageWidth": 438,
      "imageHeight": 1228,
      "connectors": [
        [ 168, 103 ],
        [ 383, 1177 ]
      ]
    },
    {
      "id": "neck-bone",
      "imageWidth": 224,
      "imageHeight": 229,
      "connectors": [
        [ 132, 57 ],
        [ 131, 200 ]
      ]
    },
    {
      "id": "thumb-bone-right",
      "imageWidth": 119,
      "imageHeight": 319,
      "connectors": [
        [ 45, 25 ]
      ]
    },
    {
      "id": "upper-arm-bone-left",
      "imageWidth": 262,
      "imageHeight": 1075,
      "connectors": [
        [ 121, 85 ],
        [ 155, 1000 ]
      ]
    },
    {
      "id": "upper-arm-bone-right",
      "imageWidth": 378,
      "imageHeight": 1155,
      "connectors": [
        [ 280, 86 ],
        [ 153, 1080 ]
      ]
    }
  ]
}
